toshi/__init__.py
toshi/code.py
toshi-0.0.5.dist-info/LICENSE
toshi-0.0.5.dist-info/METADATA
toshi-0.0.5.dist-info/WHEEL
toshi-0.0.5.dist-info/top_level.txt
toshi-0.0.5.dist-info/RECORD
