Metadata-Version: 2.1
Name: toshi
Version: 0.0.5
Summary: A package to install machine learning, deep learning packages
Home-page: https://github.com/toshihiroryuu/toshi_PyPI_package
Author: Athul Mathew Konoor
Author-email: athulmathewkonoor@gmail.com
License: UNKNOWN
Platform: UNKNOWN
Classifier: Programming Language :: Python :: 3
Classifier: License :: OSI Approved :: MIT License
Classifier: Operating System :: OS Independent
Requires-Python: >=3.6
